{"state_code":"US_DEMO","lsir_score":"0-23","count":"1","time_window":"1m","supervision_type":"PAROLE","district":"bismarck"}
{"state_code":"US_DEMO","lsir_score":"0-23","count":"1","time_window":"1m","supervision_type":"PAROLE","district":"jamestown"}
{"state_code":"US_DEMO","lsir_score":"0-23","count":"2","time_window":"1m","supervision_type":"PAROLE","district":"minot"}
{"state_code":"US_DEMO","lsir_score":"0-23","count":"0","time_window":"1m","supervision_type":"PAROLE","district":"fargo"}
{"state_code":"US_DEMO","lsir_score":"0-23","count":"0","time_window":"1m","supervision_type":"PAROLE","district":"grand-forks"}
{"state_code":"US_DEMO","lsir_score":"0-23","count":"0","time_window":"1m","supervision_type":"PAROLE","district":"devils-lake"}
{"state_code":"US_DEMO","lsir_score":"0-23","count":"0","time_window":"1m","supervision_type":"PAROLE","district":"wahpeton"}
{"state_code":"US_DEMO","lsir_score":"0-23","count":"1","time_window":"1m","supervision_type":"PAROLE","district":"rolla"}
{"state_code":"US_DEMO","lsir_score":"0-23","count":"0","time_window":"1m","supervision_type":"PAROLE","district":"washburn"}
{"state_code":"US_DEMO","lsir_score":"0-23","count":"1","time_window":"1m","supervision_type":"PAROLE","district":"williston"}
{"state_code":"US_DEMO","lsir_score":"0-23","count":"1","time_window":"1m","supervision_type":"PAROLE","district":"dickson"}
{"state_code":"US_DEMO","lsir_score":"0-23","count":"1","time_window":"1m","supervision_type":"PAROLE","district":"grafton"}
{"state_code":"US_DEMO","lsir_score":"0-23","count":"0","time_window":"1m","supervision_type":"PAROLE","district":"mandan"}
{"state_code":"US_DEMO","lsir_score":"0-23","count":"2","time_window":"1m","supervision_type":"PAROLE","district":"bottineau"}
{"state_code":"US_DEMO","lsir_score":"0-23","count":"0","time_window":"1m","supervision_type":"PAROLE","district":"oakes"}
{"state_code":"US_DEMO","lsir_score":"0-23","count":"0","time_window":"1m","supervision_type":"PAROLE","district":"beulah"}
{"state_code":"US_DEMO","lsir_score":"0-23","count":"1","time_window":"1m","supervision_type":"PROBATION","district":"bismarck"}
{"state_code":"US_DEMO","lsir_score":"0-23","count":"0","time_window":"1m","supervision_type":"PROBATION","district":"jamestown"}
{"state_code":"US_DEMO","lsir_score":"0-23","count":"1","time_window":"1m","supervision_type":"PROBATION","district":"minot"}
{"state_code":"US_DEMO","lsir_score":"0-23","count":"0","time_window":"1m","supervision_type":"PROBATION","district":"fargo"}
{"state_code":"US_DEMO","lsir_score":"0-23","count":"1","time_window":"1m","supervision_type":"PROBATION","district":"grand-forks"}
{"state_code":"US_DEMO","lsir_score":"0-23","count":"0","time_window":"1m","supervision_type":"PROBATION","district":"devils-lake"}
{"state_code":"US_DEMO","lsir_score":"0-23","count":"0","time_window":"1m","supervision_type":"PROBATION","district":"wahpeton"}
{"state_code":"US_DEMO","lsir_score":"0-23","count":"0","time_window":"1m","supervision_type":"PROBATION","district":"rolla"}
{"state_code":"US_DEMO","lsir_score":"0-23","count":"2","time_window":"1m","supervision_type":"PROBATION","district":"washburn"}
{"state_code":"US_DEMO","lsir_score":"0-23","count":"0","time_window":"1m","supervision_type":"PROBATION","district":"williston"}
{"state_code":"US_DEMO","lsir_score":"0-23","count":"0","time_window":"1m","supervision_type":"PROBATION","district":"dickson"}
{"state_code":"US_DEMO","lsir_score":"0-23","count":"0","time_window":"1m","supervision_type":"PROBATION","district":"grafton"}
{"state_code":"US_DEMO","lsir_score":"0-23","count":"0","time_window":"1m","supervision_type":"PROBATION","district":"mandan"}
{"state_code":"US_DEMO","lsir_score":"0-23","count":"1","time_window":"1m","supervision_type":"PROBATION","district":"bottineau"}
{"state_code":"US_DEMO","lsir_score":"0-23","count":"1","time_window":"1m","supervision_type":"PROBATION","district":"oakes"}
{"state_code":"US_DEMO","lsir_score":"0-23","count":"0","time_window":"1m","supervision_type":"PROBATION","district":"beulah"}
{"state_code":"US_DEMO","lsir_score":"24-29","count":"1","time_window":"1m","supervision_type":"PAROLE","district":"bismarck"}
{"state_code":"US_DEMO","lsir_score":"24-29","count":"1","time_window":"1m","supervision_type":"PAROLE","district":"jamestown"}
{"state_code":"US_DEMO","lsir_score":"24-29","count":"0","time_window":"1m","supervision_type":"PAROLE","district":"minot"}
{"state_code":"US_DEMO","lsir_score":"24-29","count":"1","time_window":"1m","supervision_type":"PAROLE","district":"fargo"}
{"state_code":"US_DEMO","lsir_score":"24-29","count":"2","time_window":"1m","supervision_type":"PAROLE","district":"grand-forks"}
{"state_code":"US_DEMO","lsir_score":"24-29","count":"2","time_window":"1m","supervision_type":"PAROLE","district":"devils-lake"}
{"state_code":"US_DEMO","lsir_score":"24-29","count":"1","time_window":"1m","supervision_type":"PAROLE","district":"wahpeton"}
{"state_code":"US_DEMO","lsir_score":"24-29","count":"1","time_window":"1m","supervision_type":"PAROLE","district":"rolla"}
{"state_code":"US_DEMO","lsir_score":"24-29","count":"1","time_window":"1m","supervision_type":"PAROLE","district":"washburn"}
{"state_code":"US_DEMO","lsir_score":"24-29","count":"2","time_window":"1m","supervision_type":"PAROLE","district":"williston"}
{"state_code":"US_DEMO","lsir_score":"24-29","count":"0","time_window":"1m","supervision_type":"PAROLE","district":"dickson"}
{"state_code":"US_DEMO","lsir_score":"24-29","count":"0","time_window":"1m","supervision_type":"PAROLE","district":"grafton"}
{"state_code":"US_DEMO","lsir_score":"24-29","count":"1","time_window":"1m","supervision_type":"PAROLE","district":"mandan"}
{"state_code":"US_DEMO","lsir_score":"24-29","count":"1","time_window":"1m","supervision_type":"PAROLE","district":"bottineau"}
{"state_code":"US_DEMO","lsir_score":"24-29","count":"5","time_window":"1m","supervision_type":"PAROLE","district":"oakes"}
{"state_code":"US_DEMO","lsir_score":"24-29","count":"0","time_window":"1m","supervision_type":"PAROLE","district":"beulah"}
{"state_code":"US_DEMO","lsir_score":"24-29","count":"0","time_window":"1m","supervision_type":"PROBATION","district":"bismarck"}
{"state_code":"US_DEMO","lsir_score":"24-29","count":"0","time_window":"1m","supervision_type":"PROBATION","district":"jamestown"}
{"state_code":"US_DEMO","lsir_score":"24-29","count":"0","time_window":"1m","supervision_type":"PROBATION","district":"minot"}
{"state_code":"US_DEMO","lsir_score":"24-29","count":"1","time_window":"1m","supervision_type":"PROBATION","district":"fargo"}
{"state_code":"US_DEMO","lsir_score":"24-29","count":"2","time_window":"1m","supervision_type":"PROBATION","district":"grand-forks"}
{"state_code":"US_DEMO","lsir_score":"24-29","count":"1","time_window":"1m","supervision_type":"PROBATION","district":"devils-lake"}
{"state_code":"US_DEMO","lsir_score":"24-29","count":"1","time_window":"1m","supervision_type":"PROBATION","district":"wahpeton"}
{"state_code":"US_DEMO","lsir_score":"24-29","count":"0","time_window":"1m","supervision_type":"PROBATION","district":"rolla"}
{"state_code":"US_DEMO","lsir_score":"24-29","count":"1","time_window":"1m","supervision_type":"PROBATION","district":"washburn"}
{"state_code":"US_DEMO","lsir_score":"24-29","count":"1","time_window":"1m","supervision_type":"PROBATION","district":"williston"}
{"state_code":"US_DEMO","lsir_score":"24-29","count":"0","time_window":"1m","supervision_type":"PROBATION","district":"dickson"}
{"state_code":"US_DEMO","lsir_score":"24-29","count":"3","time_window":"1m","supervision_type":"PROBATION","district":"grafton"}
{"state_code":"US_DEMO","lsir_score":"24-29","count":"1","time_window":"1m","supervision_type":"PROBATION","district":"mandan"}
{"state_code":"US_DEMO","lsir_score":"24-29","count":"0","time_window":"1m","supervision_type":"PROBATION","district":"bottineau"}
{"state_code":"US_DEMO","lsir_score":"24-29","count":"0","time_window":"1m","supervision_type":"PROBATION","district":"oakes"}
{"state_code":"US_DEMO","lsir_score":"24-29","count":"0","time_window":"1m","supervision_type":"PROBATION","district":"beulah"}
{"state_code":"US_DEMO","lsir_score":"30-38","count":"0","time_window":"1m","supervision_type":"PAROLE","district":"bismarck"}
{"state_code":"US_DEMO","lsir_score":"30-38","count":"2","time_window":"1m","supervision_type":"PAROLE","district":"jamestown"}
{"state_code":"US_DEMO","lsir_score":"30-38","count":"3","time_window":"1m","supervision_type":"PAROLE","district":"minot"}
{"state_code":"US_DEMO","lsir_score":"30-38","count":"1","time_window":"1m","supervision_type":"PAROLE","district":"fargo"}
{"state_code":"US_DEMO","lsir_score":"30-38","count":"3","time_window":"1m","supervision_type":"PAROLE","district":"grand-forks"}
{"state_code":"US_DEMO","lsir_score":"30-38","count":"3","time_window":"1m","supervision_type":"PAROLE","district":"devils-lake"}
{"state_code":"US_DEMO","lsir_score":"30-38","count":"2","time_window":"1m","supervision_type":"PAROLE","district":"wahpeton"}
{"state_code":"US_DEMO","lsir_score":"30-38","count":"0","time_window":"1m","supervision_type":"PAROLE","district":"rolla"}
{"state_code":"US_DEMO","lsir_score":"30-38","count":"1","time_window":"1m","supervision_type":"PAROLE","district":"washburn"}
{"state_code":"US_DEMO","lsir_score":"30-38","count":"4","time_window":"1m","supervision_type":"PAROLE","district":"williston"}
{"state_code":"US_DEMO","lsir_score":"30-38","count":"0","time_window":"1m","supervision_type":"PAROLE","district":"dickson"}
{"state_code":"US_DEMO","lsir_score":"30-38","count":"0","time_window":"1m","supervision_type":"PAROLE","district":"grafton"}
{"state_code":"US_DEMO","lsir_score":"30-38","count":"3","time_window":"1m","supervision_type":"PAROLE","district":"mandan"}
{"state_code":"US_DEMO","lsir_score":"30-38","count":"4","time_window":"1m","supervision_type":"PAROLE","district":"bottineau"}
{"state_code":"US_DEMO","lsir_score":"30-38","count":"2","time_window":"1m","supervision_type":"PAROLE","district":"oakes"}
{"state_code":"US_DEMO","lsir_score":"30-38","count":"0","time_window":"1m","supervision_type":"PAROLE","district":"beulah"}
{"state_code":"US_DEMO","lsir_score":"30-38","count":"1","time_window":"1m","supervision_type":"PROBATION","district":"bismarck"}
{"state_code":"US_DEMO","lsir_score":"30-38","count":"1","time_window":"1m","supervision_type":"PROBATION","district":"jamestown"}
{"state_code":"US_DEMO","lsir_score":"30-38","count":"1","time_window":"1m","supervision_type":"PROBATION","district":"minot"}
{"state_code":"US_DEMO","lsir_score":"30-38","count":"2","time_window":"1m","supervision_type":"PROBATION","district":"fargo"}
{"state_code":"US_DEMO","lsir_score":"30-38","count":"1","time_window":"1m","supervision_type":"PROBATION","district":"grand-forks"}
{"state_code":"US_DEMO","lsir_score":"30-38","count":"1","time_window":"1m","supervision_type":"PROBATION","district":"devils-lake"}
{"state_code":"US_DEMO","lsir_score":"30-38","count":"1","time_window":"1m","supervision_type":"PROBATION","district":"wahpeton"}
{"state_code":"US_DEMO","lsir_score":"30-38","count":"0","time_window":"1m","supervision_type":"PROBATION","district":"rolla"}
{"state_code":"US_DEMO","lsir_score":"30-38","count":"0","time_window":"1m","supervision_type":"PROBATION","district":"washburn"}
{"state_code":"US_DEMO","lsir_score":"30-38","count":"0","time_window":"1m","supervision_type":"PROBATION","district":"williston"}
{"state_code":"US_DEMO","lsir_score":"30-38","count":"1","time_window":"1m","supervision_type":"PROBATION","district":"dickson"}
{"state_code":"US_DEMO","lsir_score":"30-38","count":"1","time_window":"1m","supervision_type":"PROBATION","district":"grafton"}
{"state_code":"US_DEMO","lsir_score":"30-38","count":"1","time_window":"1m","supervision_type":"PROBATION","district":"mandan"}
{"state_code":"US_DEMO","lsir_score":"30-38","count":"1","time_window":"1m","supervision_type":"PROBATION","district":"bottineau"}
{"state_code":"US_DEMO","lsir_score":"30-38","count":"3","time_window":"1m","supervision_type":"PROBATION","district":"oakes"}
{"state_code":"US_DEMO","lsir_score":"30-38","count":"0","time_window":"1m","supervision_type":"PROBATION","district":"beulah"}
{"state_code":"US_DEMO","lsir_score":"39+","count":"0","time_window":"1m","supervision_type":"PAROLE","district":"bismarck"}
{"state_code":"US_DEMO","lsir_score":"39+","count":"1","time_window":"1m","supervision_type":"PAROLE","district":"jamestown"}
{"state_code":"US_DEMO","lsir_score":"39+","count":"0","time_window":"1m","supervision_type":"PAROLE","district":"minot"}
{"state_code":"US_DEMO","lsir_score":"39+","count":"1","time_window":"1m","supervision_type":"PAROLE","district":"fargo"}
{"state_code":"US_DEMO","lsir_score":"39+","count":"0","time_window":"1m","supervision_type":"PAROLE","district":"grand-forks"}
{"state_code":"US_DEMO","lsir_score":"39+","count":"0","time_window":"1m","supervision_type":"PAROLE","district":"devils-lake"}
{"state_code":"US_DEMO","lsir_score":"39+","count":"2","time_window":"1m","supervision_type":"PAROLE","district":"wahpeton"}
{"state_code":"US_DEMO","lsir_score":"39+","count":"1","time_window":"1m","supervision_type":"PAROLE","district":"rolla"}
{"state_code":"US_DEMO","lsir_score":"39+","count":"1","time_window":"1m","supervision_type":"PAROLE","district":"washburn"}
{"state_code":"US_DEMO","lsir_score":"39+","count":"1","time_window":"1m","supervision_type":"PAROLE","district":"williston"}
{"state_code":"US_DEMO","lsir_score":"39+","count":"1","time_window":"1m","supervision_type":"PAROLE","district":"dickson"}
{"state_code":"US_DEMO","lsir_score":"39+","count":"0","time_window":"1m","supervision_type":"PAROLE","district":"grafton"}
{"state_code":"US_DEMO","lsir_score":"39+","count":"1","time_window":"1m","supervision_type":"PAROLE","district":"mandan"}
{"state_code":"US_DEMO","lsir_score":"39+","count":"0","time_window":"1m","supervision_type":"PAROLE","district":"bottineau"}
{"state_code":"US_DEMO","lsir_score":"39+","count":"0","time_window":"1m","supervision_type":"PAROLE","district":"oakes"}
{"state_code":"US_DEMO","lsir_score":"39+","count":"1","time_window":"1m","supervision_type":"PAROLE","district":"beulah"}
{"state_code":"US_DEMO","lsir_score":"39+","count":"1","time_window":"1m","supervision_type":"PROBATION","district":"bismarck"}
{"state_code":"US_DEMO","lsir_score":"39+","count":"3","time_window":"1m","supervision_type":"PROBATION","district":"jamestown"}
{"state_code":"US_DEMO","lsir_score":"39+","count":"2","time_window":"1m","supervision_type":"PROBATION","district":"minot"}
{"state_code":"US_DEMO","lsir_score":"39+","count":"2","time_window":"1m","supervision_type":"PROBATION","district":"fargo"}
{"state_code":"US_DEMO","lsir_score":"39+","count":"0","time_window":"1m","supervision_type":"PROBATION","district":"grand-forks"}
{"state_code":"US_DEMO","lsir_score":"39+","count":"2","time_window":"1m","supervision_type":"PROBATION","district":"devils-lake"}
{"state_code":"US_DEMO","lsir_score":"39+","count":"3","time_window":"1m","supervision_type":"PROBATION","district":"wahpeton"}
{"state_code":"US_DEMO","lsir_score":"39+","count":"0","time_window":"1m","supervision_type":"PROBATION","district":"rolla"}
{"state_code":"US_DEMO","lsir_score":"39+","count":"1","time_window":"1m","supervision_type":"PROBATION","district":"washburn"}
{"state_code":"US_DEMO","lsir_score":"39+","count":"0","time_window":"1m","supervision_type":"PROBATION","district":"williston"}
{"state_code":"US_DEMO","lsir_score":"39+","count":"0","time_window":"1m","supervision_type":"PROBATION","district":"dickson"}
{"state_code":"US_DEMO","lsir_score":"39+","count":"1","time_window":"1m","supervision_type":"PROBATION","district":"grafton"}
{"state_code":"US_DEMO","lsir_score":"39+","count":"0","time_window":"1m","supervision_type":"PROBATION","district":"mandan"}
{"state_code":"US_DEMO","lsir_score":"39+","count":"1","time_window":"1m","supervision_type":"PROBATION","district":"bottineau"}
{"state_code":"US_DEMO","lsir_score":"39+","count":"1","time_window":"1m","supervision_type":"PROBATION","district":"oakes"}
{"state_code":"US_DEMO","lsir_score":"39+","count":"2","time_window":"1m","supervision_type":"PROBATION","district":"beulah"}
{"state_code":"US_DEMO","lsir_score":"0-23","count":"0","time_window":"3m","supervision_type":"PAROLE","district":"bismarck"}
{"state_code":"US_DEMO","lsir_score":"0-23","count":"0","time_window":"3m","supervision_type":"PAROLE","district":"jamestown"}
{"state_code":"US_DEMO","lsir_score":"0-23","count":"0","time_window":"3m","supervision_type":"PAROLE","district":"minot"}
{"state_code":"US_DEMO","lsir_score":"0-23","count":"1","time_window":"3m","supervision_type":"PAROLE","district":"fargo"}
{"state_code":"US_DEMO","lsir_score":"0-23","count":"0","time_window":"3m","supervision_type":"PAROLE","district":"grand-forks"}
{"state_code":"US_DEMO","lsir_score":"0-23","count":"0","time_window":"3m","supervision_type":"PAROLE","district":"devils-lake"}
{"state_code":"US_DEMO","lsir_score":"0-23","count":"0","time_window":"3m","supervision_type":"PAROLE","district":"wahpeton"}
{"state_code":"US_DEMO","lsir_score":"0-23","count":"0","time_window":"3m","supervision_type":"PAROLE","district":"rolla"}
{"state_code":"US_DEMO","lsir_score":"0-23","count":"0","time_window":"3m","supervision_type":"PAROLE","district":"washburn"}
{"state_code":"US_DEMO","lsir_score":"0-23","count":"0","time_window":"3m","supervision_type":"PAROLE","district":"williston"}
{"state_code":"US_DEMO","lsir_score":"0-23","count":"0","time_window":"3m","supervision_type":"PAROLE","district":"dickson"}
{"state_code":"US_DEMO","lsir_score":"0-23","count":"1","time_window":"3m","supervision_type":"PAROLE","district":"grafton"}
{"state_code":"US_DEMO","lsir_score":"0-23","count":"1","time_window":"3m","supervision_type":"PAROLE","district":"mandan"}
{"state_code":"US_DEMO","lsir_score":"0-23","count":"0","time_window":"3m","supervision_type":"PAROLE","district":"bottineau"}
{"state_code":"US_DEMO","lsir_score":"0-23","count":"2","time_window":"3m","supervision_type":"PAROLE","district":"oakes"}
{"state_code":"US_DEMO","lsir_score":"0-23","count":"0","time_window":"3m","supervision_type":"PAROLE","district":"beulah"}
{"state_code":"US_DEMO","lsir_score":"0-23","count":"6","time_window":"3m","supervision_type":"PROBATION","district":"bismarck"}
{"state_code":"US_DEMO","lsir_score":"0-23","count":"11","time_window":"3m","supervision_type":"PROBATION","district":"jamestown"}
{"state_code":"US_DEMO","lsir_score":"0-23","count":"0","time_window":"3m","supervision_type":"PROBATION","district":"minot"}
{"state_code":"US_DEMO","lsir_score":"0-23","count":"4","time_window":"3m","supervision_type":"PROBATION","district":"fargo"}
{"state_code":"US_DEMO","lsir_score":"0-23","count":"0","time_window":"3m","supervision_type":"PROBATION","district":"grand-forks"}
{"state_code":"US_DEMO","lsir_score":"0-23","count":"10","time_window":"3m","supervision_type":"PROBATION","district":"devils-lake"}
{"state_code":"US_DEMO","lsir_score":"0-23","count":"2","time_window":"3m","supervision_type":"PROBATION","district":"wahpeton"}
{"state_code":"US_DEMO","lsir_score":"0-23","count":"1","time_window":"3m","supervision_type":"PROBATION","district":"rolla"}
{"state_code":"US_DEMO","lsir_score":"0-23","count":"2","time_window":"3m","supervision_type":"PROBATION","district":"washburn"}
{"state_code":"US_DEMO","lsir_score":"0-23","count":"1","time_window":"3m","supervision_type":"PROBATION","district":"williston"}
{"state_code":"US_DEMO","lsir_score":"0-23","count":"2","time_window":"3m","supervision_type":"PROBATION","district":"dickson"}
{"state_code":"US_DEMO","lsir_score":"0-23","count":"1","time_window":"3m","supervision_type":"PROBATION","district":"grafton"}
{"state_code":"US_DEMO","lsir_score":"0-23","count":"2","time_window":"3m","supervision_type":"PROBATION","district":"mandan"}
{"state_code":"US_DEMO","lsir_score":"0-23","count":"1","time_window":"3m","supervision_type":"PROBATION","district":"bottineau"}
{"state_code":"US_DEMO","lsir_score":"0-23","count":"0","time_window":"3m","supervision_type":"PROBATION","district":"oakes"}
{"state_code":"US_DEMO","lsir_score":"0-23","count":"1","time_window":"3m","supervision_type":"PROBATION","district":"beulah"}
{"state_code":"US_DEMO","lsir_score":"24-29","count":"0","time_window":"3m","supervision_type":"PAROLE","district":"bismarck"}
{"state_code":"US_DEMO","lsir_score":"24-29","count":"2","time_window":"3m","supervision_type":"PAROLE","district":"jamestown"}
{"state_code":"US_DEMO","lsir_score":"24-29","count":"2","time_window":"3m","supervision_type":"PAROLE","district":"minot"}
{"state_code":"US_DEMO","lsir_score":"24-29","count":"0","time_window":"3m","supervision_type":"PAROLE","district":"fargo"}
{"state_code":"US_DEMO","lsir_score":"24-29","count":"2","time_window":"3m","supervision_type":"PAROLE","district":"grand-forks"}
{"state_code":"US_DEMO","lsir_score":"24-29","count":"1","time_window":"3m","supervision_type":"PAROLE","district":"devils-lake"}
{"state_code":"US_DEMO","lsir_score":"24-29","count":"1","time_window":"3m","supervision_type":"PAROLE","district":"wahpeton"}
{"state_code":"US_DEMO","lsir_score":"24-29","count":"5","time_window":"3m","supervision_type":"PAROLE","district":"rolla"}
{"state_code":"US_DEMO","lsir_score":"24-29","count":"1","time_window":"3m","supervision_type":"PAROLE","district":"washburn"}
{"state_code":"US_DEMO","lsir_score":"24-29","count":"0","time_window":"3m","supervision_type":"PAROLE","district":"williston"}
{"state_code":"US_DEMO","lsir_score":"24-29","count":"1","time_window":"3m","supervision_type":"PAROLE","district":"dickson"}
{"state_code":"US_DEMO","lsir_score":"24-29","count":"2","time_window":"3m","supervision_type":"PAROLE","district":"grafton"}
{"state_code":"US_DEMO","lsir_score":"24-29","count":"2","time_window":"3m","supervision_type":"PAROLE","district":"mandan"}
{"state_code":"US_DEMO","lsir_score":"24-29","count":"1","time_window":"3m","supervision_type":"PAROLE","district":"bottineau"}
{"state_code":"US_DEMO","lsir_score":"24-29","count":"1","time_window":"3m","supervision_type":"PAROLE","district":"oakes"}
{"state_code":"US_DEMO","lsir_score":"24-29","count":"0","time_window":"3m","supervision_type":"PAROLE","district":"beulah"}
{"state_code":"US_DEMO","lsir_score":"24-29","count":"7","time_window":"3m","supervision_type":"PROBATION","district":"bismarck"}
{"state_code":"US_DEMO","lsir_score":"24-29","count":"3","time_window":"3m","supervision_type":"PROBATION","district":"jamestown"}
{"state_code":"US_DEMO","lsir_score":"24-29","count":"7","time_window":"3m","supervision_type":"PROBATION","district":"minot"}
{"state_code":"US_DEMO","lsir_score":"24-29","count":"4","time_window":"3m","supervision_type":"PROBATION","district":"fargo"}
{"state_code":"US_DEMO","lsir_score":"24-29","count":"14","time_window":"3m","supervision_type":"PROBATION","district":"grand-forks"}
{"state_code":"US_DEMO","lsir_score":"24-29","count":"5","time_window":"3m","supervision_type":"PROBATION","district":"devils-lake"}
{"state_code":"US_DEMO","lsir_score":"24-29","count":"2","time_window":"3m","supervision_type":"PROBATION","district":"wahpeton"}
{"state_code":"US_DEMO","lsir_score":"24-29","count":"1","time_window":"3m","supervision_type":"PROBATION","district":"rolla"}
{"state_code":"US_DEMO","lsir_score":"24-29","count":"1","time_window":"3m","supervision_type":"PROBATION","district":"washburn"}
{"state_code":"US_DEMO","lsir_score":"24-29","count":"4","time_window":"3m","supervision_type":"PROBATION","district":"williston"}
{"state_code":"US_DEMO","lsir_score":"24-29","count":"8","time_window":"3m","supervision_type":"PROBATION","district":"dickson"}
{"state_code":"US_DEMO","lsir_score":"24-29","count":"2","time_window":"3m","supervision_type":"PROBATION","district":"grafton"}
{"state_code":"US_DEMO","lsir_score":"24-29","count":"4","time_window":"3m","supervision_type":"PROBATION","district":"mandan"}
{"state_code":"US_DEMO","lsir_score":"24-29","count":"1","time_window":"3m","supervision_type":"PROBATION","district":"bottineau"}
{"state_code":"US_DEMO","lsir_score":"24-29","count":"7","time_window":"3m","supervision_type":"PROBATION","district":"oakes"}
{"state_code":"US_DEMO","lsir_score":"24-29","count":"1","time_window":"3m","supervision_type":"PROBATION","district":"beulah"}
{"state_code":"US_DEMO","lsir_score":"30-38","count":"11","time_window":"3m","supervision_type":"PAROLE","district":"bismarck"}
{"state_code":"US_DEMO","lsir_score":"30-38","count":"11","time_window":"3m","supervision_type":"PAROLE","district":"jamestown"}
{"state_code":"US_DEMO","lsir_score":"30-38","count":"7","time_window":"3m","supervision_type":"PAROLE","district":"minot"}
{"state_code":"US_DEMO","lsir_score":"30-38","count":"26","time_window":"3m","supervision_type":"PAROLE","district":"fargo"}
{"state_code":"US_DEMO","lsir_score":"30-38","count":"0","time_window":"3m","supervision_type":"PAROLE","district":"grand-forks"}
{"state_code":"US_DEMO","lsir_score":"30-38","count":"2","time_window":"3m","supervision_type":"PAROLE","district":"devils-lake"}
{"state_code":"US_DEMO","lsir_score":"30-38","count":"8","time_window":"3m","supervision_type":"PAROLE","district":"wahpeton"}
{"state_code":"US_DEMO","lsir_score":"30-38","count":"7","time_window":"3m","supervision_type":"PAROLE","district":"rolla"}
{"state_code":"US_DEMO","lsir_score":"30-38","count":"5","time_window":"3m","supervision_type":"PAROLE","district":"washburn"}
{"state_code":"US_DEMO","lsir_score":"30-38","count":"5","time_window":"3m","supervision_type":"PAROLE","district":"williston"}
{"state_code":"US_DEMO","lsir_score":"30-38","count":"10","time_window":"3m","supervision_type":"PAROLE","district":"dickson"}
{"state_code":"US_DEMO","lsir_score":"30-38","count":"4","time_window":"3m","supervision_type":"PAROLE","district":"grafton"}
{"state_code":"US_DEMO","lsir_score":"30-38","count":"5","time_window":"3m","supervision_type":"PAROLE","district":"mandan"}
{"state_code":"US_DEMO","lsir_score":"30-38","count":"9","time_window":"3m","supervision_type":"PAROLE","district":"bottineau"}
{"state_code":"US_DEMO","lsir_score":"30-38","count":"8","time_window":"3m","supervision_type":"PAROLE","district":"oakes"}
{"state_code":"US_DEMO","lsir_score":"30-38","count":"15","time_window":"3m","supervision_type":"PAROLE","district":"beulah"}
{"state_code":"US_DEMO","lsir_score":"30-38","count":"0","time_window":"3m","supervision_type":"PROBATION","district":"bismarck"}
{"state_code":"US_DEMO","lsir_score":"30-38","count":"0","time_window":"3m","supervision_type":"PROBATION","district":"jamestown"}
{"state_code":"US_DEMO","lsir_score":"30-38","count":"0","time_window":"3m","supervision_type":"PROBATION","district":"minot"}
{"state_code":"US_DEMO","lsir_score":"30-38","count":"0","time_window":"3m","supervision_type":"PROBATION","district":"fargo"}
{"state_code":"US_DEMO","lsir_score":"30-38","count":"0","time_window":"3m","supervision_type":"PROBATION","district":"grand-forks"}
{"state_code":"US_DEMO","lsir_score":"30-38","count":"0","time_window":"3m","supervision_type":"PROBATION","district":"devils-lake"}
{"state_code":"US_DEMO","lsir_score":"30-38","count":"0","time_window":"3m","supervision_type":"PROBATION","district":"wahpeton"}
{"state_code":"US_DEMO","lsir_score":"30-38","count":"0","time_window":"3m","supervision_type":"PROBATION","district":"rolla"}
{"state_code":"US_DEMO","lsir_score":"30-38","count":"0","time_window":"3m","supervision_type":"PROBATION","district":"washburn"}
{"state_code":"US_DEMO","lsir_score":"30-38","count":"0","time_window":"3m","supervision_type":"PROBATION","district":"williston"}
{"state_code":"US_DEMO","lsir_score":"30-38","count":"0","time_window":"3m","supervision_type":"PROBATION","district":"dickson"}
{"state_code":"US_DEMO","lsir_score":"30-38","count":"1","time_window":"3m","supervision_type":"PROBATION","district":"grafton"}
{"state_code":"US_DEMO","lsir_score":"30-38","count":"0","time_window":"3m","supervision_type":"PROBATION","district":"mandan"}
{"state_code":"US_DEMO","lsir_score":"30-38","count":"0","time_window":"3m","supervision_type":"PROBATION","district":"bottineau"}
{"state_code":"US_DEMO","lsir_score":"30-38","count":"0","time_window":"3m","supervision_type":"PROBATION","district":"oakes"}
{"state_code":"US_DEMO","lsir_score":"30-38","count":"0","time_window":"3m","supervision_type":"PROBATION","district":"beulah"}
{"state_code":"US_DEMO","lsir_score":"39+","count":"1","time_window":"3m","supervision_type":"PAROLE","district":"bismarck"}
{"state_code":"US_DEMO","lsir_score":"39+","count":"2","time_window":"3m","supervision_type":"PAROLE","district":"jamestown"}
{"state_code":"US_DEMO","lsir_score":"39+","count":"1","time_window":"3m","supervision_type":"PAROLE","district":"minot"}
{"state_code":"US_DEMO","lsir_score":"39+","count":"0","time_window":"3m","supervision_type":"PAROLE","district":"fargo"}
{"state_code":"US_DEMO","lsir_score":"39+","count":"0","time_window":"3m","supervision_type":"PAROLE","district":"grand-forks"}
{"state_code":"US_DEMO","lsir_score":"39+","count":"5","time_window":"3m","supervision_type":"PAROLE","district":"devils-lake"}
{"state_code":"US_DEMO","lsir_score":"39+","count":"2","time_window":"3m","supervision_type":"PAROLE","district":"wahpeton"}
{"state_code":"US_DEMO","lsir_score":"39+","count":"2","time_window":"3m","supervision_type":"PAROLE","district":"rolla"}
{"state_code":"US_DEMO","lsir_score":"39+","count":"4","time_window":"3m","supervision_type":"PAROLE","district":"washburn"}
{"state_code":"US_DEMO","lsir_score":"39+","count":"4","time_window":"3m","supervision_type":"PAROLE","district":"williston"}
{"state_code":"US_DEMO","lsir_score":"39+","count":"3","time_window":"3m","supervision_type":"PAROLE","district":"dickson"}
{"state_code":"US_DEMO","lsir_score":"39+","count":"0","time_window":"3m","supervision_type":"PAROLE","district":"grafton"}
{"state_code":"US_DEMO","lsir_score":"39+","count":"5","time_window":"3m","supervision_type":"PAROLE","district":"mandan"}
{"state_code":"US_DEMO","lsir_score":"39+","count":"1","time_window":"3m","supervision_type":"PAROLE","district":"bottineau"}
{"state_code":"US_DEMO","lsir_score":"39+","count":"0","time_window":"3m","supervision_type":"PAROLE","district":"oakes"}
{"state_code":"US_DEMO","lsir_score":"39+","count":"2","time_window":"3m","supervision_type":"PAROLE","district":"beulah"}
{"state_code":"US_DEMO","lsir_score":"39+","count":"4","time_window":"3m","supervision_type":"PROBATION","district":"bismarck"}
{"state_code":"US_DEMO","lsir_score":"39+","count":"3","time_window":"3m","supervision_type":"PROBATION","district":"jamestown"}
{"state_code":"US_DEMO","lsir_score":"39+","count":"7","time_window":"3m","supervision_type":"PROBATION","district":"minot"}
{"state_code":"US_DEMO","lsir_score":"39+","count":"11","time_window":"3m","supervision_type":"PROBATION","district":"fargo"}
{"state_code":"US_DEMO","lsir_score":"39+","count":"10","time_window":"3m","supervision_type":"PROBATION","district":"grand-forks"}
{"state_code":"US_DEMO","lsir_score":"39+","count":"3","time_window":"3m","supervision_type":"PROBATION","district":"devils-lake"}
{"state_code":"US_DEMO","lsir_score":"39+","count":"5","time_window":"3m","supervision_type":"PROBATION","district":"wahpeton"}
{"state_code":"US_DEMO","lsir_score":"39+","count":"1","time_window":"3m","supervision_type":"PROBATION","district":"rolla"}
{"state_code":"US_DEMO","lsir_score":"39+","count":"1","time_window":"3m","supervision_type":"PROBATION","district":"washburn"}
{"state_code":"US_DEMO","lsir_score":"39+","count":"7","time_window":"3m","supervision_type":"PROBATION","district":"williston"}
{"state_code":"US_DEMO","lsir_score":"39+","count":"1","time_window":"3m","supervision_type":"PROBATION","district":"dickson"}
{"state_code":"US_DEMO","lsir_score":"39+","count":"7","time_window":"3m","supervision_type":"PROBATION","district":"grafton"}
{"state_code":"US_DEMO","lsir_score":"39+","count":"0","time_window":"3m","supervision_type":"PROBATION","district":"mandan"}
{"state_code":"US_DEMO","lsir_score":"39+","count":"1","time_window":"3m","supervision_type":"PROBATION","district":"bottineau"}
{"state_code":"US_DEMO","lsir_score":"39+","count":"1","time_window":"3m","supervision_type":"PROBATION","district":"oakes"}
{"state_code":"US_DEMO","lsir_score":"39+","count":"1","time_window":"3m","supervision_type":"PROBATION","district":"beulah"}
{"state_code":"US_DEMO","lsir_score":"0-23","count":"3","time_window":"6m","supervision_type":"PAROLE","district":"bismarck"}
{"state_code":"US_DEMO","lsir_score":"0-23","count":"5","time_window":"6m","supervision_type":"PAROLE","district":"jamestown"}
{"state_code":"US_DEMO","lsir_score":"0-23","count":"10","time_window":"6m","supervision_type":"PAROLE","district":"minot"}
{"state_code":"US_DEMO","lsir_score":"0-23","count":"1","time_window":"6m","supervision_type":"PAROLE","district":"fargo"}
{"state_code":"US_DEMO","lsir_score":"0-23","count":"4","time_window":"6m","supervision_type":"PAROLE","district":"grand-forks"}
{"state_code":"US_DEMO","lsir_score":"0-23","count":"1","time_window":"6m","supervision_type":"PAROLE","district":"devils-lake"}
{"state_code":"US_DEMO","lsir_score":"0-23","count":"2","time_window":"6m","supervision_type":"PAROLE","district":"wahpeton"}
{"state_code":"US_DEMO","lsir_score":"0-23","count":"0","time_window":"6m","supervision_type":"PAROLE","district":"rolla"}
{"state_code":"US_DEMO","lsir_score":"0-23","count":"3","time_window":"6m","supervision_type":"PAROLE","district":"washburn"}
{"state_code":"US_DEMO","lsir_score":"0-23","count":"9","time_window":"6m","supervision_type":"PAROLE","district":"williston"}
{"state_code":"US_DEMO","lsir_score":"0-23","count":"4","time_window":"6m","supervision_type":"PAROLE","district":"dickson"}
{"state_code":"US_DEMO","lsir_score":"0-23","count":"2","time_window":"6m","supervision_type":"PAROLE","district":"grafton"}
{"state_code":"US_DEMO","lsir_score":"0-23","count":"2","time_window":"6m","supervision_type":"PAROLE","district":"mandan"}
{"state_code":"US_DEMO","lsir_score":"0-23","count":"1","time_window":"6m","supervision_type":"PAROLE","district":"bottineau"}
{"state_code":"US_DEMO","lsir_score":"0-23","count":"1","time_window":"6m","supervision_type":"PAROLE","district":"oakes"}
{"state_code":"US_DEMO","lsir_score":"0-23","count":"3","time_window":"6m","supervision_type":"PAROLE","district":"beulah"}
{"state_code":"US_DEMO","lsir_score":"0-23","count":"0","time_window":"6m","supervision_type":"PROBATION","district":"bismarck"}
{"state_code":"US_DEMO","lsir_score":"0-23","count":"1","time_window":"6m","supervision_type":"PROBATION","district":"jamestown"}
{"state_code":"US_DEMO","lsir_score":"0-23","count":"7","time_window":"6m","supervision_type":"PROBATION","district":"minot"}
{"state_code":"US_DEMO","lsir_score":"0-23","count":"1","time_window":"6m","supervision_type":"PROBATION","district":"fargo"}
{"state_code":"US_DEMO","lsir_score":"0-23","count":"1","time_window":"6m","supervision_type":"PROBATION","district":"grand-forks"}
{"state_code":"US_DEMO","lsir_score":"0-23","count":"2","time_window":"6m","supervision_type":"PROBATION","district":"devils-lake"}
{"state_code":"US_DEMO","lsir_score":"0-23","count":"2","time_window":"6m","supervision_type":"PROBATION","district":"wahpeton"}
{"state_code":"US_DEMO","lsir_score":"0-23","count":"2","time_window":"6m","supervision_type":"PROBATION","district":"rolla"}
{"state_code":"US_DEMO","lsir_score":"0-23","count":"0","time_window":"6m","supervision_type":"PROBATION","district":"washburn"}
{"state_code":"US_DEMO","lsir_score":"0-23","count":"0","time_window":"6m","supervision_type":"PROBATION","district":"williston"}
{"state_code":"US_DEMO","lsir_score":"0-23","count":"1","time_window":"6m","supervision_type":"PROBATION","district":"dickson"}
{"state_code":"US_DEMO","lsir_score":"0-23","count":"1","time_window":"6m","supervision_type":"PROBATION","district":"grafton"}
{"state_code":"US_DEMO","lsir_score":"0-23","count":"1","time_window":"6m","supervision_type":"PROBATION","district":"mandan"}
{"state_code":"US_DEMO","lsir_score":"0-23","count":"2","time_window":"6m","supervision_type":"PROBATION","district":"bottineau"}
{"state_code":"US_DEMO","lsir_score":"0-23","count":"1","time_window":"6m","supervision_type":"PROBATION","district":"oakes"}
{"state_code":"US_DEMO","lsir_score":"0-23","count":"1","time_window":"6m","supervision_type":"PROBATION","district":"beulah"}
{"state_code":"US_DEMO","lsir_score":"24-29","count":"1","time_window":"6m","supervision_type":"PAROLE","district":"bismarck"}
{"state_code":"US_DEMO","lsir_score":"24-29","count":"0","time_window":"6m","supervision_type":"PAROLE","district":"jamestown"}
{"state_code":"US_DEMO","lsir_score":"24-29","count":"1","time_window":"6m","supervision_type":"PAROLE","district":"minot"}
{"state_code":"US_DEMO","lsir_score":"24-29","count":"2","time_window":"6m","supervision_type":"PAROLE","district":"fargo"}
{"state_code":"US_DEMO","lsir_score":"24-29","count":"0","time_window":"6m","supervision_type":"PAROLE","district":"grand-forks"}
{"state_code":"US_DEMO","lsir_score":"24-29","count":"1","time_window":"6m","supervision_type":"PAROLE","district":"devils-lake"}
{"state_code":"US_DEMO","lsir_score":"24-29","count":"2","time_window":"6m","supervision_type":"PAROLE","district":"wahpeton"}
{"state_code":"US_DEMO","lsir_score":"24-29","count":"2","time_window":"6m","supervision_type":"PAROLE","district":"rolla"}
{"state_code":"US_DEMO","lsir_score":"24-29","count":"0","time_window":"6m","supervision_type":"PAROLE","district":"washburn"}
{"state_code":"US_DEMO","lsir_score":"24-29","count":"1","time_window":"6m","supervision_type":"PAROLE","district":"williston"}
{"state_code":"US_DEMO","lsir_score":"24-29","count":"0","time_window":"6m","supervision_type":"PAROLE","district":"dickson"}
{"state_code":"US_DEMO","lsir_score":"24-29","count":"0","time_window":"6m","supervision_type":"PAROLE","district":"grafton"}
{"state_code":"US_DEMO","lsir_score":"24-29","count":"0","time_window":"6m","supervision_type":"PAROLE","district":"mandan"}
{"state_code":"US_DEMO","lsir_score":"24-29","count":"1","time_window":"6m","supervision_type":"PAROLE","district":"bottineau"}
{"state_code":"US_DEMO","lsir_score":"24-29","count":"0","time_window":"6m","supervision_type":"PAROLE","district":"oakes"}
{"state_code":"US_DEMO","lsir_score":"24-29","count":"1","time_window":"6m","supervision_type":"PAROLE","district":"beulah"}
{"state_code":"US_DEMO","lsir_score":"24-29","count":"1","time_window":"6m","supervision_type":"PROBATION","district":"bismarck"}
{"state_code":"US_DEMO","lsir_score":"24-29","count":"8","time_window":"6m","supervision_type":"PROBATION","district":"jamestown"}
{"state_code":"US_DEMO","lsir_score":"24-29","count":"2","time_window":"6m","supervision_type":"PROBATION","district":"minot"}
{"state_code":"US_DEMO","lsir_score":"24-29","count":"8","time_window":"6m","supervision_type":"PROBATION","district":"fargo"}
{"state_code":"US_DEMO","lsir_score":"24-29","count":"11","time_window":"6m","supervision_type":"PROBATION","district":"grand-forks"}
{"state_code":"US_DEMO","lsir_score":"24-29","count":"29","time_window":"6m","supervision_type":"PROBATION","district":"devils-lake"}
{"state_code":"US_DEMO","lsir_score":"24-29","count":"6","time_window":"6m","supervision_type":"PROBATION","district":"wahpeton"}
{"state_code":"US_DEMO","lsir_score":"24-29","count":"2","time_window":"6m","supervision_type":"PROBATION","district":"rolla"}
{"state_code":"US_DEMO","lsir_score":"24-29","count":"1","time_window":"6m","supervision_type":"PROBATION","district":"washburn"}
{"state_code":"US_DEMO","lsir_score":"24-29","count":"7","time_window":"6m","supervision_type":"PROBATION","district":"williston"}
{"state_code":"US_DEMO","lsir_score":"24-29","count":"1","time_window":"6m","supervision_type":"PROBATION","district":"dickson"}
{"state_code":"US_DEMO","lsir_score":"24-29","count":"13","time_window":"6m","supervision_type":"PROBATION","district":"grafton"}
{"state_code":"US_DEMO","lsir_score":"24-29","count":"28","time_window":"6m","supervision_type":"PROBATION","district":"mandan"}
{"state_code":"US_DEMO","lsir_score":"24-29","count":"2","time_window":"6m","supervision_type":"PROBATION","district":"bottineau"}
{"state_code":"US_DEMO","lsir_score":"24-29","count":"7","time_window":"6m","supervision_type":"PROBATION","district":"oakes"}
{"state_code":"US_DEMO","lsir_score":"24-29","count":"16","time_window":"6m","supervision_type":"PROBATION","district":"beulah"}
{"state_code":"US_DEMO","lsir_score":"30-38","count":"12","time_window":"6m","supervision_type":"PAROLE","district":"bismarck"}
{"state_code":"US_DEMO","lsir_score":"30-38","count":"10","time_window":"6m","supervision_type":"PAROLE","district":"jamestown"}
{"state_code":"US_DEMO","lsir_score":"30-38","count":"25","time_window":"6m","supervision_type":"PAROLE","district":"minot"}
{"state_code":"US_DEMO","lsir_score":"30-38","count":"1","time_window":"6m","supervision_type":"PAROLE","district":"fargo"}
{"state_code":"US_DEMO","lsir_score":"30-38","count":"4","time_window":"6m","supervision_type":"PAROLE","district":"grand-forks"}
{"state_code":"US_DEMO","lsir_score":"30-38","count":"4","time_window":"6m","supervision_type":"PAROLE","district":"devils-lake"}
{"state_code":"US_DEMO","lsir_score":"30-38","count":"29","time_window":"6m","supervision_type":"PAROLE","district":"wahpeton"}
{"state_code":"US_DEMO","lsir_score":"30-38","count":"15","time_window":"6m","supervision_type":"PAROLE","district":"rolla"}
{"state_code":"US_DEMO","lsir_score":"30-38","count":"2","time_window":"6m","supervision_type":"PAROLE","district":"washburn"}
{"state_code":"US_DEMO","lsir_score":"30-38","count":"2","time_window":"6m","supervision_type":"PAROLE","district":"williston"}
{"state_code":"US_DEMO","lsir_score":"30-38","count":"5","time_window":"6m","supervision_type":"PAROLE","district":"dickson"}
{"state_code":"US_DEMO","lsir_score":"30-38","count":"0","time_window":"6m","supervision_type":"PAROLE","district":"grafton"}
{"state_code":"US_DEMO","lsir_score":"30-38","count":"6","time_window":"6m","supervision_type":"PAROLE","district":"mandan"}
{"state_code":"US_DEMO","lsir_score":"30-38","count":"11","time_window":"6m","supervision_type":"PAROLE","district":"bottineau"}
{"state_code":"US_DEMO","lsir_score":"30-38","count":"11","time_window":"6m","supervision_type":"PAROLE","district":"oakes"}
{"state_code":"US_DEMO","lsir_score":"30-38","count":"17","time_window":"6m","supervision_type":"PAROLE","district":"beulah"}
{"state_code":"US_DEMO","lsir_score":"30-38","count":"5","time_window":"6m","supervision_type":"PROBATION","district":"bismarck"}
{"state_code":"US_DEMO","lsir_score":"30-38","count":"9","time_window":"6m","supervision_type":"PROBATION","district":"jamestown"}
{"state_code":"US_DEMO","lsir_score":"30-38","count":"8","time_window":"6m","supervision_type":"PROBATION","district":"minot"}
{"state_code":"US_DEMO","lsir_score":"30-38","count":"12","time_window":"6m","supervision_type":"PROBATION","district":"fargo"}
{"state_code":"US_DEMO","lsir_score":"30-38","count":"6","time_window":"6m","supervision_type":"PROBATION","district":"grand-forks"}
{"state_code":"US_DEMO","lsir_score":"30-38","count":"13","time_window":"6m","supervision_type":"PROBATION","district":"devils-lake"}
{"state_code":"US_DEMO","lsir_score":"30-38","count":"10","time_window":"6m","supervision_type":"PROBATION","district":"wahpeton"}
{"state_code":"US_DEMO","lsir_score":"30-38","count":"5","time_window":"6m","supervision_type":"PROBATION","district":"rolla"}
{"state_code":"US_DEMO","lsir_score":"30-38","count":"2","time_window":"6m","supervision_type":"PROBATION","district":"washburn"}
{"state_code":"US_DEMO","lsir_score":"30-38","count":"21","time_window":"6m","supervision_type":"PROBATION","district":"williston"}
{"state_code":"US_DEMO","lsir_score":"30-38","count":"6","time_window":"6m","supervision_type":"PROBATION","district":"dickson"}
{"state_code":"US_DEMO","lsir_score":"30-38","count":"1","time_window":"6m","supervision_type":"PROBATION","district":"grafton"}
{"state_code":"US_DEMO","lsir_score":"30-38","count":"6","time_window":"6m","supervision_type":"PROBATION","district":"mandan"}
{"state_code":"US_DEMO","lsir_score":"30-38","count":"1","time_window":"6m","supervision_type":"PROBATION","district":"bottineau"}
{"state_code":"US_DEMO","lsir_score":"30-38","count":"14","time_window":"6m","supervision_type":"PROBATION","district":"oakes"}
{"state_code":"US_DEMO","lsir_score":"30-38","count":"12","time_window":"6m","supervision_type":"PROBATION","district":"beulah"}
{"state_code":"US_DEMO","lsir_score":"39+","count":"0","time_window":"6m","supervision_type":"PAROLE","district":"bismarck"}
{"state_code":"US_DEMO","lsir_score":"39+","count":"0","time_window":"6m","supervision_type":"PAROLE","district":"jamestown"}
{"state_code":"US_DEMO","lsir_score":"39+","count":"1","time_window":"6m","supervision_type":"PAROLE","district":"minot"}
{"state_code":"US_DEMO","lsir_score":"39+","count":"7","time_window":"6m","supervision_type":"PAROLE","district":"fargo"}
{"state_code":"US_DEMO","lsir_score":"39+","count":"3","time_window":"6m","supervision_type":"PAROLE","district":"grand-forks"}
{"state_code":"US_DEMO","lsir_score":"39+","count":"13","time_window":"6m","supervision_type":"PAROLE","district":"devils-lake"}
{"state_code":"US_DEMO","lsir_score":"39+","count":"1","time_window":"6m","supervision_type":"PAROLE","district":"wahpeton"}
{"state_code":"US_DEMO","lsir_score":"39+","count":"1","time_window":"6m","supervision_type":"PAROLE","district":"rolla"}
{"state_code":"US_DEMO","lsir_score":"39+","count":"1","time_window":"6m","supervision_type":"PAROLE","district":"washburn"}
{"state_code":"US_DEMO","lsir_score":"39+","count":"1","time_window":"6m","supervision_type":"PAROLE","district":"williston"}
{"state_code":"US_DEMO","lsir_score":"39+","count":"4","time_window":"6m","supervision_type":"PAROLE","district":"dickson"}
{"state_code":"US_DEMO","lsir_score":"39+","count":"1","time_window":"6m","supervision_type":"PAROLE","district":"grafton"}
{"state_code":"US_DEMO","lsir_score":"39+","count":"3","time_window":"6m","supervision_type":"PAROLE","district":"mandan"}
{"state_code":"US_DEMO","lsir_score":"39+","count":"1","time_window":"6m","supervision_type":"PAROLE","district":"bottineau"}
{"state_code":"US_DEMO","lsir_score":"39+","count":"4","time_window":"6m","supervision_type":"PAROLE","district":"oakes"}
{"state_code":"US_DEMO","lsir_score":"39+","count":"3","time_window":"6m","supervision_type":"PAROLE","district":"beulah"}
{"state_code":"US_DEMO","lsir_score":"39+","count":"5","time_window":"6m","supervision_type":"PROBATION","district":"bismarck"}
{"state_code":"US_DEMO","lsir_score":"39+","count":"12","time_window":"6m","supervision_type":"PROBATION","district":"jamestown"}
{"state_code":"US_DEMO","lsir_score":"39+","count":"6","time_window":"6m","supervision_type":"PROBATION","district":"minot"}
{"state_code":"US_DEMO","lsir_score":"39+","count":"2","time_window":"6m","supervision_type":"PROBATION","district":"fargo"}
{"state_code":"US_DEMO","lsir_score":"39+","count":"7","time_window":"6m","supervision_type":"PROBATION","district":"grand-forks"}
{"state_code":"US_DEMO","lsir_score":"39+","count":"9","time_window":"6m","supervision_type":"PROBATION","district":"devils-lake"}
{"state_code":"US_DEMO","lsir_score":"39+","count":"18","time_window":"6m","supervision_type":"PROBATION","district":"wahpeton"}
{"state_code":"US_DEMO","lsir_score":"39+","count":"10","time_window":"6m","supervision_type":"PROBATION","district":"rolla"}
{"state_code":"US_DEMO","lsir_score":"39+","count":"15","time_window":"6m","supervision_type":"PROBATION","district":"washburn"}
{"state_code":"US_DEMO","lsir_score":"39+","count":"6","time_window":"6m","supervision_type":"PROBATION","district":"williston"}
{"state_code":"US_DEMO","lsir_score":"39+","count":"8","time_window":"6m","supervision_type":"PROBATION","district":"dickson"}
{"state_code":"US_DEMO","lsir_score":"39+","count":"5","time_window":"6m","supervision_type":"PROBATION","district":"grafton"}
{"state_code":"US_DEMO","lsir_score":"39+","count":"15","time_window":"6m","supervision_type":"PROBATION","district":"mandan"}
{"state_code":"US_DEMO","lsir_score":"39+","count":"13","time_window":"6m","supervision_type":"PROBATION","district":"bottineau"}
{"state_code":"US_DEMO","lsir_score":"39+","count":"24","time_window":"6m","supervision_type":"PROBATION","district":"oakes"}
{"state_code":"US_DEMO","lsir_score":"39+","count":"1","time_window":"6m","supervision_type":"PROBATION","district":"beulah"}
{"state_code":"US_DEMO","lsir_score":"0-23","count":"1","time_window":"1y","supervision_type":"PAROLE","district":"bismarck"}
{"state_code":"US_DEMO","lsir_score":"0-23","count":"0","time_window":"1y","supervision_type":"PAROLE","district":"jamestown"}
{"state_code":"US_DEMO","lsir_score":"0-23","count":"1","time_window":"1y","supervision_type":"PAROLE","district":"minot"}
{"state_code":"US_DEMO","lsir_score":"0-23","count":"2","time_window":"1y","supervision_type":"PAROLE","district":"fargo"}
{"state_code":"US_DEMO","lsir_score":"0-23","count":"5","time_window":"1y","supervision_type":"PAROLE","district":"grand-forks"}
{"state_code":"US_DEMO","lsir_score":"0-23","count":"8","time_window":"1y","supervision_type":"PAROLE","district":"devils-lake"}
{"state_code":"US_DEMO","lsir_score":"0-23","count":"1","time_window":"1y","supervision_type":"PAROLE","district":"wahpeton"}
{"state_code":"US_DEMO","lsir_score":"0-23","count":"3","time_window":"1y","supervision_type":"PAROLE","district":"rolla"}
{"state_code":"US_DEMO","lsir_score":"0-23","count":"3","time_window":"1y","supervision_type":"PAROLE","district":"washburn"}
{"state_code":"US_DEMO","lsir_score":"0-23","count":"3","time_window":"1y","supervision_type":"PAROLE","district":"williston"}
{"state_code":"US_DEMO","lsir_score":"0-23","count":"2","time_window":"1y","supervision_type":"PAROLE","district":"dickson"}
{"state_code":"US_DEMO","lsir_score":"0-23","count":"5","time_window":"1y","supervision_type":"PAROLE","district":"grafton"}
{"state_code":"US_DEMO","lsir_score":"0-23","count":"1","time_window":"1y","supervision_type":"PAROLE","district":"mandan"}
{"state_code":"US_DEMO","lsir_score":"0-23","count":"1","time_window":"1y","supervision_type":"PAROLE","district":"bottineau"}
{"state_code":"US_DEMO","lsir_score":"0-23","count":"4","time_window":"1y","supervision_type":"PAROLE","district":"oakes"}
{"state_code":"US_DEMO","lsir_score":"0-23","count":"1","time_window":"1y","supervision_type":"PAROLE","district":"beulah"}
{"state_code":"US_DEMO","lsir_score":"0-23","count":"19","time_window":"1y","supervision_type":"PROBATION","district":"bismarck"}
{"state_code":"US_DEMO","lsir_score":"0-23","count":"0","time_window":"1y","supervision_type":"PROBATION","district":"jamestown"}
{"state_code":"US_DEMO","lsir_score":"0-23","count":"2","time_window":"1y","supervision_type":"PROBATION","district":"minot"}
{"state_code":"US_DEMO","lsir_score":"0-23","count":"0","time_window":"1y","supervision_type":"PROBATION","district":"fargo"}
{"state_code":"US_DEMO","lsir_score":"0-23","count":"7","time_window":"1y","supervision_type":"PROBATION","district":"grand-forks"}
{"state_code":"US_DEMO","lsir_score":"0-23","count":"1","time_window":"1y","supervision_type":"PROBATION","district":"devils-lake"}
{"state_code":"US_DEMO","lsir_score":"0-23","count":"8","time_window":"1y","supervision_type":"PROBATION","district":"wahpeton"}
{"state_code":"US_DEMO","lsir_score":"0-23","count":"7","time_window":"1y","supervision_type":"PROBATION","district":"rolla"}
{"state_code":"US_DEMO","lsir_score":"0-23","count":"2","time_window":"1y","supervision_type":"PROBATION","district":"washburn"}
{"state_code":"US_DEMO","lsir_score":"0-23","count":"1","time_window":"1y","supervision_type":"PROBATION","district":"williston"}
{"state_code":"US_DEMO","lsir_score":"0-23","count":"7","time_window":"1y","supervision_type":"PROBATION","district":"dickson"}
{"state_code":"US_DEMO","lsir_score":"0-23","count":"5","time_window":"1y","supervision_type":"PROBATION","district":"grafton"}
{"state_code":"US_DEMO","lsir_score":"0-23","count":"2","time_window":"1y","supervision_type":"PROBATION","district":"mandan"}
{"state_code":"US_DEMO","lsir_score":"0-23","count":"16","time_window":"1y","supervision_type":"PROBATION","district":"bottineau"}
{"state_code":"US_DEMO","lsir_score":"0-23","count":"3","time_window":"1y","supervision_type":"PROBATION","district":"oakes"}
{"state_code":"US_DEMO","lsir_score":"0-23","count":"5","time_window":"1y","supervision_type":"PROBATION","district":"beulah"}
{"state_code":"US_DEMO","lsir_score":"24-29","count":"10","time_window":"1y","supervision_type":"PAROLE","district":"bismarck"}
{"state_code":"US_DEMO","lsir_score":"24-29","count":"1","time_window":"1y","supervision_type":"PAROLE","district":"jamestown"}
{"state_code":"US_DEMO","lsir_score":"24-29","count":"1","time_window":"1y","supervision_type":"PAROLE","district":"minot"}
{"state_code":"US_DEMO","lsir_score":"24-29","count":"2","time_window":"1y","supervision_type":"PAROLE","district":"fargo"}
{"state_code":"US_DEMO","lsir_score":"24-29","count":"5","time_window":"1y","supervision_type":"PAROLE","district":"grand-forks"}
{"state_code":"US_DEMO","lsir_score":"24-29","count":"10","time_window":"1y","supervision_type":"PAROLE","district":"devils-lake"}
{"state_code":"US_DEMO","lsir_score":"24-29","count":"6","time_window":"1y","supervision_type":"PAROLE","district":"wahpeton"}
{"state_code":"US_DEMO","lsir_score":"24-29","count":"6","time_window":"1y","supervision_type":"PAROLE","district":"rolla"}
{"state_code":"US_DEMO","lsir_score":"24-29","count":"4","time_window":"1y","supervision_type":"PAROLE","district":"washburn"}
{"state_code":"US_DEMO","lsir_score":"24-29","count":"1","time_window":"1y","supervision_type":"PAROLE","district":"williston"}
{"state_code":"US_DEMO","lsir_score":"24-29","count":"1","time_window":"1y","supervision_type":"PAROLE","district":"dickson"}
{"state_code":"US_DEMO","lsir_score":"24-29","count":"3","time_window":"1y","supervision_type":"PAROLE","district":"grafton"}
{"state_code":"US_DEMO","lsir_score":"24-29","count":"3","time_window":"1y","supervision_type":"PAROLE","district":"mandan"}
{"state_code":"US_DEMO","lsir_score":"24-29","count":"11","time_window":"1y","supervision_type":"PAROLE","district":"bottineau"}
{"state_code":"US_DEMO","lsir_score":"24-29","count":"5","time_window":"1y","supervision_type":"PAROLE","district":"oakes"}
{"state_code":"US_DEMO","lsir_score":"24-29","count":"4","time_window":"1y","supervision_type":"PAROLE","district":"beulah"}
{"state_code":"US_DEMO","lsir_score":"24-29","count":"1","time_window":"1y","supervision_type":"PROBATION","district":"bismarck"}
{"state_code":"US_DEMO","lsir_score":"24-29","count":"14","time_window":"1y","supervision_type":"PROBATION","district":"jamestown"}
{"state_code":"US_DEMO","lsir_score":"24-29","count":"9","time_window":"1y","supervision_type":"PROBATION","district":"minot"}
{"state_code":"US_DEMO","lsir_score":"24-29","count":"6","time_window":"1y","supervision_type":"PROBATION","district":"fargo"}
{"state_code":"US_DEMO","lsir_score":"24-29","count":"5","time_window":"1y","supervision_type":"PROBATION","district":"grand-forks"}
{"state_code":"US_DEMO","lsir_score":"24-29","count":"65","time_window":"1y","supervision_type":"PROBATION","district":"devils-lake"}
{"state_code":"US_DEMO","lsir_score":"24-29","count":"6","time_window":"1y","supervision_type":"PROBATION","district":"wahpeton"}
{"state_code":"US_DEMO","lsir_score":"24-29","count":"14","time_window":"1y","supervision_type":"PROBATION","district":"rolla"}
{"state_code":"US_DEMO","lsir_score":"24-29","count":"19","time_window":"1y","supervision_type":"PROBATION","district":"washburn"}
{"state_code":"US_DEMO","lsir_score":"24-29","count":"3","time_window":"1y","supervision_type":"PROBATION","district":"williston"}
{"state_code":"US_DEMO","lsir_score":"24-29","count":"18","time_window":"1y","supervision_type":"PROBATION","district":"dickson"}
{"state_code":"US_DEMO","lsir_score":"24-29","count":"3","time_window":"1y","supervision_type":"PROBATION","district":"grafton"}
{"state_code":"US_DEMO","lsir_score":"24-29","count":"12","time_window":"1y","supervision_type":"PROBATION","district":"mandan"}
{"state_code":"US_DEMO","lsir_score":"24-29","count":"9","time_window":"1y","supervision_type":"PROBATION","district":"bottineau"}
{"state_code":"US_DEMO","lsir_score":"24-29","count":"13","time_window":"1y","supervision_type":"PROBATION","district":"oakes"}
{"state_code":"US_DEMO","lsir_score":"24-29","count":"29","time_window":"1y","supervision_type":"PROBATION","district":"beulah"}
{"state_code":"US_DEMO","lsir_score":"30-38","count":"16","time_window":"1y","supervision_type":"PAROLE","district":"bismarck"}
{"state_code":"US_DEMO","lsir_score":"30-38","count":"24","time_window":"1y","supervision_type":"PAROLE","district":"jamestown"}
{"state_code":"US_DEMO","lsir_score":"30-38","count":"2","time_window":"1y","supervision_type":"PAROLE","district":"minot"}
{"state_code":"US_DEMO","lsir_score":"30-38","count":"38","time_window":"1y","supervision_type":"PAROLE","district":"fargo"}
{"state_code":"US_DEMO","lsir_score":"30-38","count":"28","time_window":"1y","supervision_type":"PAROLE","district":"grand-forks"}
{"state_code":"US_DEMO","lsir_score":"30-38","count":"1","time_window":"1y","supervision_type":"PAROLE","district":"devils-lake"}
{"state_code":"US_DEMO","lsir_score":"30-38","count":"15","time_window":"1y","supervision_type":"PAROLE","district":"wahpeton"}
{"state_code":"US_DEMO","lsir_score":"30-38","count":"9","time_window":"1y","supervision_type":"PAROLE","district":"rolla"}
{"state_code":"US_DEMO","lsir_score":"30-38","count":"10","time_window":"1y","supervision_type":"PAROLE","district":"washburn"}
{"state_code":"US_DEMO","lsir_score":"30-38","count":"14","time_window":"1y","supervision_type":"PAROLE","district":"williston"}
{"state_code":"US_DEMO","lsir_score":"30-38","count":"16","time_window":"1y","supervision_type":"PAROLE","district":"dickson"}
{"state_code":"US_DEMO","lsir_score":"30-38","count":"9","time_window":"1y","supervision_type":"PAROLE","district":"grafton"}
{"state_code":"US_DEMO","lsir_score":"30-38","count":"50","time_window":"1y","supervision_type":"PAROLE","district":"mandan"}
{"state_code":"US_DEMO","lsir_score":"30-38","count":"70","time_window":"1y","supervision_type":"PAROLE","district":"bottineau"}
{"state_code":"US_DEMO","lsir_score":"30-38","count":"76","time_window":"1y","supervision_type":"PAROLE","district":"oakes"}
{"state_code":"US_DEMO","lsir_score":"30-38","count":"24","time_window":"1y","supervision_type":"PAROLE","district":"beulah"}
{"state_code":"US_DEMO","lsir_score":"30-38","count":"8","time_window":"1y","supervision_type":"PROBATION","district":"bismarck"}
{"state_code":"US_DEMO","lsir_score":"30-38","count":"0","time_window":"1y","supervision_type":"PROBATION","district":"jamestown"}
{"state_code":"US_DEMO","lsir_score":"30-38","count":"10","time_window":"1y","supervision_type":"PROBATION","district":"minot"}
{"state_code":"US_DEMO","lsir_score":"30-38","count":"8","time_window":"1y","supervision_type":"PROBATION","district":"fargo"}
{"state_code":"US_DEMO","lsir_score":"30-38","count":"17","time_window":"1y","supervision_type":"PROBATION","district":"grand-forks"}
{"state_code":"US_DEMO","lsir_score":"30-38","count":"21","time_window":"1y","supervision_type":"PROBATION","district":"devils-lake"}
{"state_code":"US_DEMO","lsir_score":"30-38","count":"33","time_window":"1y","supervision_type":"PROBATION","district":"wahpeton"}
{"state_code":"US_DEMO","lsir_score":"30-38","count":"5","time_window":"1y","supervision_type":"PROBATION","district":"rolla"}
{"state_code":"US_DEMO","lsir_score":"30-38","count":"5","time_window":"1y","supervision_type":"PROBATION","district":"washburn"}
{"state_code":"US_DEMO","lsir_score":"30-38","count":"51","time_window":"1y","supervision_type":"PROBATION","district":"williston"}
{"state_code":"US_DEMO","lsir_score":"30-38","count":"5","time_window":"1y","supervision_type":"PROBATION","district":"dickson"}
{"state_code":"US_DEMO","lsir_score":"30-38","count":"1","time_window":"1y","supervision_type":"PROBATION","district":"grafton"}
{"state_code":"US_DEMO","lsir_score":"30-38","count":"5","time_window":"1y","supervision_type":"PROBATION","district":"mandan"}
{"state_code":"US_DEMO","lsir_score":"30-38","count":"1","time_window":"1y","supervision_type":"PROBATION","district":"bottineau"}
{"state_code":"US_DEMO","lsir_score":"30-38","count":"5","time_window":"1y","supervision_type":"PROBATION","district":"oakes"}
{"state_code":"US_DEMO","lsir_score":"30-38","count":"25","time_window":"1y","supervision_type":"PROBATION","district":"beulah"}
{"state_code":"US_DEMO","lsir_score":"39+","count":"24","time_window":"1y","supervision_type":"PAROLE","district":"bismarck"}
{"state_code":"US_DEMO","lsir_score":"39+","count":"12","time_window":"1y","supervision_type":"PAROLE","district":"jamestown"}
{"state_code":"US_DEMO","lsir_score":"39+","count":"5","time_window":"1y","supervision_type":"PAROLE","district":"minot"}
{"state_code":"US_DEMO","lsir_score":"39+","count":"2","time_window":"1y","supervision_type":"PAROLE","district":"fargo"}
{"state_code":"US_DEMO","lsir_score":"39+","count":"9","time_window":"1y","supervision_type":"PAROLE","district":"grand-forks"}
{"state_code":"US_DEMO","lsir_score":"39+","count":"1","time_window":"1y","supervision_type":"PAROLE","district":"devils-lake"}
{"state_code":"US_DEMO","lsir_score":"39+","count":"2","time_window":"1y","supervision_type":"PAROLE","district":"wahpeton"}
{"state_code":"US_DEMO","lsir_score":"39+","count":"2","time_window":"1y","supervision_type":"PAROLE","district":"rolla"}
{"state_code":"US_DEMO","lsir_score":"39+","count":"4","time_window":"1y","supervision_type":"PAROLE","district":"washburn"}
{"state_code":"US_DEMO","lsir_score":"39+","count":"18","time_window":"1y","supervision_type":"PAROLE","district":"williston"}
{"state_code":"US_DEMO","lsir_score":"39+","count":"1","time_window":"1y","supervision_type":"PAROLE","district":"dickson"}
{"state_code":"US_DEMO","lsir_score":"39+","count":"1","time_window":"1y","supervision_type":"PAROLE","district":"grafton"}
{"state_code":"US_DEMO","lsir_score":"39+","count":"6","time_window":"1y","supervision_type":"PAROLE","district":"mandan"}
{"state_code":"US_DEMO","lsir_score":"39+","count":"14","time_window":"1y","supervision_type":"PAROLE","district":"bottineau"}
{"state_code":"US_DEMO","lsir_score":"39+","count":"2","time_window":"1y","supervision_type":"PAROLE","district":"oakes"}
{"state_code":"US_DEMO","lsir_score":"39+","count":"9","time_window":"1y","supervision_type":"PAROLE","district":"beulah"}
{"state_code":"US_DEMO","lsir_score":"39+","count":"20","time_window":"1y","supervision_type":"PROBATION","district":"bismarck"}
{"state_code":"US_DEMO","lsir_score":"39+","count":"8","time_window":"1y","supervision_type":"PROBATION","district":"jamestown"}
{"state_code":"US_DEMO","lsir_score":"39+","count":"38","time_window":"1y","supervision_type":"PROBATION","district":"minot"}
{"state_code":"US_DEMO","lsir_score":"39+","count":"30","time_window":"1y","supervision_type":"PROBATION","district":"fargo"}
{"state_code":"US_DEMO","lsir_score":"39+","count":"40","time_window":"1y","supervision_type":"PROBATION","district":"grand-forks"}
{"state_code":"US_DEMO","lsir_score":"39+","count":"28","time_window":"1y","supervision_type":"PROBATION","district":"devils-lake"}
{"state_code":"US_DEMO","lsir_score":"39+","count":"23","time_window":"1y","supervision_type":"PROBATION","district":"wahpeton"}
{"state_code":"US_DEMO","lsir_score":"39+","count":"13","time_window":"1y","supervision_type":"PROBATION","district":"rolla"}
{"state_code":"US_DEMO","lsir_score":"39+","count":"0","time_window":"1y","supervision_type":"PROBATION","district":"washburn"}
{"state_code":"US_DEMO","lsir_score":"39+","count":"22","time_window":"1y","supervision_type":"PROBATION","district":"williston"}
{"state_code":"US_DEMO","lsir_score":"39+","count":"8","time_window":"1y","supervision_type":"PROBATION","district":"dickson"}
{"state_code":"US_DEMO","lsir_score":"39+","count":"38","time_window":"1y","supervision_type":"PROBATION","district":"grafton"}
{"state_code":"US_DEMO","lsir_score":"39+","count":"9","time_window":"1y","supervision_type":"PROBATION","district":"mandan"}
{"state_code":"US_DEMO","lsir_score":"39+","count":"4","time_window":"1y","supervision_type":"PROBATION","district":"bottineau"}
{"state_code":"US_DEMO","lsir_score":"39+","count":"6","time_window":"1y","supervision_type":"PROBATION","district":"oakes"}
{"state_code":"US_DEMO","lsir_score":"39+","count":"1","time_window":"1y","supervision_type":"PROBATION","district":"beulah"}
{"state_code":"US_DEMO","lsir_score":"0-23","count":"25","time_window":"3y","supervision_type":"PAROLE","district":"bismarck"}
{"state_code":"US_DEMO","lsir_score":"0-23","count":"30","time_window":"3y","supervision_type":"PAROLE","district":"jamestown"}
{"state_code":"US_DEMO","lsir_score":"0-23","count":"11","time_window":"3y","supervision_type":"PAROLE","district":"minot"}
{"state_code":"US_DEMO","lsir_score":"0-23","count":"16","time_window":"3y","supervision_type":"PAROLE","district":"fargo"}
{"state_code":"US_DEMO","lsir_score":"0-23","count":"19","time_window":"3y","supervision_type":"PAROLE","district":"grand-forks"}
{"state_code":"US_DEMO","lsir_score":"0-23","count":"21","time_window":"3y","supervision_type":"PAROLE","district":"devils-lake"}
{"state_code":"US_DEMO","lsir_score":"0-23","count":"12","time_window":"3y","supervision_type":"PAROLE","district":"wahpeton"}
{"state_code":"US_DEMO","lsir_score":"0-23","count":"6","time_window":"3y","supervision_type":"PAROLE","district":"rolla"}
{"state_code":"US_DEMO","lsir_score":"0-23","count":"14","time_window":"3y","supervision_type":"PAROLE","district":"washburn"}
{"state_code":"US_DEMO","lsir_score":"0-23","count":"27","time_window":"3y","supervision_type":"PAROLE","district":"williston"}
{"state_code":"US_DEMO","lsir_score":"0-23","count":"16","time_window":"3y","supervision_type":"PAROLE","district":"dickson"}
{"state_code":"US_DEMO","lsir_score":"0-23","count":"8","time_window":"3y","supervision_type":"PAROLE","district":"grafton"}
{"state_code":"US_DEMO","lsir_score":"0-23","count":"46","time_window":"3y","supervision_type":"PAROLE","district":"mandan"}
{"state_code":"US_DEMO","lsir_score":"0-23","count":"6","time_window":"3y","supervision_type":"PAROLE","district":"bottineau"}
{"state_code":"US_DEMO","lsir_score":"0-23","count":"3","time_window":"3y","supervision_type":"PAROLE","district":"oakes"}
{"state_code":"US_DEMO","lsir_score":"0-23","count":"35","time_window":"3y","supervision_type":"PAROLE","district":"beulah"}
{"state_code":"US_DEMO","lsir_score":"0-23","count":"0","time_window":"3y","supervision_type":"PROBATION","district":"bismarck"}
{"state_code":"US_DEMO","lsir_score":"0-23","count":"1","time_window":"3y","supervision_type":"PROBATION","district":"jamestown"}
{"state_code":"US_DEMO","lsir_score":"0-23","count":"13","time_window":"3y","supervision_type":"PROBATION","district":"minot"}
{"state_code":"US_DEMO","lsir_score":"0-23","count":"7","time_window":"3y","supervision_type":"PROBATION","district":"fargo"}
{"state_code":"US_DEMO","lsir_score":"0-23","count":"1","time_window":"3y","supervision_type":"PROBATION","district":"grand-forks"}
{"state_code":"US_DEMO","lsir_score":"0-23","count":"4","time_window":"3y","supervision_type":"PROBATION","district":"devils-lake"}
{"state_code":"US_DEMO","lsir_score":"0-23","count":"1","time_window":"3y","supervision_type":"PROBATION","district":"wahpeton"}
{"state_code":"US_DEMO","lsir_score":"0-23","count":"3","time_window":"3y","supervision_type":"PROBATION","district":"rolla"}
{"state_code":"US_DEMO","lsir_score":"0-23","count":"16","time_window":"3y","supervision_type":"PROBATION","district":"washburn"}
{"state_code":"US_DEMO","lsir_score":"0-23","count":"8","time_window":"3y","supervision_type":"PROBATION","district":"williston"}
{"state_code":"US_DEMO","lsir_score":"0-23","count":"9","time_window":"3y","supervision_type":"PROBATION","district":"dickson"}
{"state_code":"US_DEMO","lsir_score":"0-23","count":"3","time_window":"3y","supervision_type":"PROBATION","district":"grafton"}
{"state_code":"US_DEMO","lsir_score":"0-23","count":"1","time_window":"3y","supervision_type":"PROBATION","district":"mandan"}
{"state_code":"US_DEMO","lsir_score":"0-23","count":"2","time_window":"3y","supervision_type":"PROBATION","district":"bottineau"}
{"state_code":"US_DEMO","lsir_score":"0-23","count":"4","time_window":"3y","supervision_type":"PROBATION","district":"oakes"}
{"state_code":"US_DEMO","lsir_score":"0-23","count":"4","time_window":"3y","supervision_type":"PROBATION","district":"beulah"}
{"state_code":"US_DEMO","lsir_score":"24-29","count":"80","time_window":"3y","supervision_type":"PAROLE","district":"bismarck"}
{"state_code":"US_DEMO","lsir_score":"24-29","count":"5","time_window":"3y","supervision_type":"PAROLE","district":"jamestown"}
{"state_code":"US_DEMO","lsir_score":"24-29","count":"12","time_window":"3y","supervision_type":"PAROLE","district":"minot"}
{"state_code":"US_DEMO","lsir_score":"24-29","count":"28","time_window":"3y","supervision_type":"PAROLE","district":"fargo"}
{"state_code":"US_DEMO","lsir_score":"24-29","count":"28","time_window":"3y","supervision_type":"PAROLE","district":"grand-forks"}
{"state_code":"US_DEMO","lsir_score":"24-29","count":"53","time_window":"3y","supervision_type":"PAROLE","district":"devils-lake"}
{"state_code":"US_DEMO","lsir_score":"24-29","count":"24","time_window":"3y","supervision_type":"PAROLE","district":"wahpeton"}
{"state_code":"US_DEMO","lsir_score":"24-29","count":"108","time_window":"3y","supervision_type":"PAROLE","district":"rolla"}
{"state_code":"US_DEMO","lsir_score":"24-29","count":"17","time_window":"3y","supervision_type":"PAROLE","district":"washburn"}
{"state_code":"US_DEMO","lsir_score":"24-29","count":"96","time_window":"3y","supervision_type":"PAROLE","district":"williston"}
{"state_code":"US_DEMO","lsir_score":"24-29","count":"23","time_window":"3y","supervision_type":"PAROLE","district":"dickson"}
{"state_code":"US_DEMO","lsir_score":"24-29","count":"34","time_window":"3y","supervision_type":"PAROLE","district":"grafton"}
{"state_code":"US_DEMO","lsir_score":"24-29","count":"57","time_window":"3y","supervision_type":"PAROLE","district":"mandan"}
{"state_code":"US_DEMO","lsir_score":"24-29","count":"113","time_window":"3y","supervision_type":"PAROLE","district":"bottineau"}
{"state_code":"US_DEMO","lsir_score":"24-29","count":"11","time_window":"3y","supervision_type":"PAROLE","district":"oakes"}
{"state_code":"US_DEMO","lsir_score":"24-29","count":"1","time_window":"3y","supervision_type":"PAROLE","district":"beulah"}
{"state_code":"US_DEMO","lsir_score":"24-29","count":"5","time_window":"3y","supervision_type":"PROBATION","district":"bismarck"}
{"state_code":"US_DEMO","lsir_score":"24-29","count":"5","time_window":"3y","supervision_type":"PROBATION","district":"jamestown"}
{"state_code":"US_DEMO","lsir_score":"24-29","count":"6","time_window":"3y","supervision_type":"PROBATION","district":"minot"}
{"state_code":"US_DEMO","lsir_score":"24-29","count":"30","time_window":"3y","supervision_type":"PROBATION","district":"fargo"}
{"state_code":"US_DEMO","lsir_score":"24-29","count":"8","time_window":"3y","supervision_type":"PROBATION","district":"grand-forks"}
{"state_code":"US_DEMO","lsir_score":"24-29","count":"4","time_window":"3y","supervision_type":"PROBATION","district":"devils-lake"}
{"state_code":"US_DEMO","lsir_score":"24-29","count":"26","time_window":"3y","supervision_type":"PROBATION","district":"wahpeton"}
{"state_code":"US_DEMO","lsir_score":"24-29","count":"8","time_window":"3y","supervision_type":"PROBATION","district":"rolla"}
{"state_code":"US_DEMO","lsir_score":"24-29","count":"26","time_window":"3y","supervision_type":"PROBATION","district":"washburn"}
{"state_code":"US_DEMO","lsir_score":"24-29","count":"4","time_window":"3y","supervision_type":"PROBATION","district":"williston"}
{"state_code":"US_DEMO","lsir_score":"24-29","count":"10","time_window":"3y","supervision_type":"PROBATION","district":"dickson"}
{"state_code":"US_DEMO","lsir_score":"24-29","count":"16","time_window":"3y","supervision_type":"PROBATION","district":"grafton"}
{"state_code":"US_DEMO","lsir_score":"24-29","count":"9","time_window":"3y","supervision_type":"PROBATION","district":"mandan"}
{"state_code":"US_DEMO","lsir_score":"24-29","count":"36","time_window":"3y","supervision_type":"PROBATION","district":"bottineau"}
{"state_code":"US_DEMO","lsir_score":"24-29","count":"8","time_window":"3y","supervision_type":"PROBATION","district":"oakes"}
{"state_code":"US_DEMO","lsir_score":"24-29","count":"14","time_window":"3y","supervision_type":"PROBATION","district":"beulah"}
{"state_code":"US_DEMO","lsir_score":"30-38","count":"133","time_window":"3y","supervision_type":"PAROLE","district":"bismarck"}
{"state_code":"US_DEMO","lsir_score":"30-38","count":"245","time_window":"3y","supervision_type":"PAROLE","district":"jamestown"}
{"state_code":"US_DEMO","lsir_score":"30-38","count":"35","time_window":"3y","supervision_type":"PAROLE","district":"minot"}
{"state_code":"US_DEMO","lsir_score":"30-38","count":"84","time_window":"3y","supervision_type":"PAROLE","district":"fargo"}
{"state_code":"US_DEMO","lsir_score":"30-38","count":"2","time_window":"3y","supervision_type":"PAROLE","district":"grand-forks"}
{"state_code":"US_DEMO","lsir_score":"30-38","count":"105","time_window":"3y","supervision_type":"PAROLE","district":"devils-lake"}
{"state_code":"US_DEMO","lsir_score":"30-38","count":"12","time_window":"3y","supervision_type":"PAROLE","district":"wahpeton"}
{"state_code":"US_DEMO","lsir_score":"30-38","count":"10","time_window":"3y","supervision_type":"PAROLE","district":"rolla"}
{"state_code":"US_DEMO","lsir_score":"30-38","count":"6","time_window":"3y","supervision_type":"PAROLE","district":"washburn"}
{"state_code":"US_DEMO","lsir_score":"30-38","count":"208","time_window":"3y","supervision_type":"PAROLE","district":"williston"}
{"state_code":"US_DEMO","lsir_score":"30-38","count":"59","time_window":"3y","supervision_type":"PAROLE","district":"dickson"}
{"state_code":"US_DEMO","lsir_score":"30-38","count":"175","time_window":"3y","supervision_type":"PAROLE","district":"grafton"}
{"state_code":"US_DEMO","lsir_score":"30-38","count":"190","time_window":"3y","supervision_type":"PAROLE","district":"mandan"}
{"state_code":"US_DEMO","lsir_score":"30-38","count":"108","time_window":"3y","supervision_type":"PAROLE","district":"bottineau"}
{"state_code":"US_DEMO","lsir_score":"30-38","count":"48","time_window":"3y","supervision_type":"PAROLE","district":"oakes"}
{"state_code":"US_DEMO","lsir_score":"30-38","count":"23","time_window":"3y","supervision_type":"PAROLE","district":"beulah"}
{"state_code":"US_DEMO","lsir_score":"30-38","count":"14","time_window":"3y","supervision_type":"PROBATION","district":"bismarck"}
{"state_code":"US_DEMO","lsir_score":"30-38","count":"22","time_window":"3y","supervision_type":"PROBATION","district":"jamestown"}
{"state_code":"US_DEMO","lsir_score":"30-38","count":"21","time_window":"3y","supervision_type":"PROBATION","district":"minot"}
{"state_code":"US_DEMO","lsir_score":"30-38","count":"39","time_window":"3y","supervision_type":"PROBATION","district":"fargo"}
{"state_code":"US_DEMO","lsir_score":"30-38","count":"66","time_window":"3y","supervision_type":"PROBATION","district":"grand-forks"}
{"state_code":"US_DEMO","lsir_score":"30-38","count":"83","time_window":"3y","supervision_type":"PROBATION","district":"devils-lake"}
{"state_code":"US_DEMO","lsir_score":"30-38","count":"3","time_window":"3y","supervision_type":"PROBATION","district":"wahpeton"}
{"state_code":"US_DEMO","lsir_score":"30-38","count":"42","time_window":"3y","supervision_type":"PROBATION","district":"rolla"}
{"state_code":"US_DEMO","lsir_score":"30-38","count":"17","time_window":"3y","supervision_type":"PROBATION","district":"washburn"}
{"state_code":"US_DEMO","lsir_score":"30-38","count":"48","time_window":"3y","supervision_type":"PROBATION","district":"williston"}
{"state_code":"US_DEMO","lsir_score":"30-38","count":"19","time_window":"3y","supervision_type":"PROBATION","district":"dickson"}
{"state_code":"US_DEMO","lsir_score":"30-38","count":"17","time_window":"3y","supervision_type":"PROBATION","district":"grafton"}
{"state_code":"US_DEMO","lsir_score":"30-38","count":"3","time_window":"3y","supervision_type":"PROBATION","district":"mandan"}
{"state_code":"US_DEMO","lsir_score":"30-38","count":"6","time_window":"3y","supervision_type":"PROBATION","district":"bottineau"}
{"state_code":"US_DEMO","lsir_score":"30-38","count":"39","time_window":"3y","supervision_type":"PROBATION","district":"oakes"}
{"state_code":"US_DEMO","lsir_score":"30-38","count":"35","time_window":"3y","supervision_type":"PROBATION","district":"beulah"}
{"state_code":"US_DEMO","lsir_score":"39+","count":"9","time_window":"3y","supervision_type":"PAROLE","district":"bismarck"}
{"state_code":"US_DEMO","lsir_score":"39+","count":"4","time_window":"3y","supervision_type":"PAROLE","district":"jamestown"}
{"state_code":"US_DEMO","lsir_score":"39+","count":"5","time_window":"3y","supervision_type":"PAROLE","district":"minot"}
{"state_code":"US_DEMO","lsir_score":"39+","count":"2","time_window":"3y","supervision_type":"PAROLE","district":"fargo"}
{"state_code":"US_DEMO","lsir_score":"39+","count":"78","time_window":"3y","supervision_type":"PAROLE","district":"grand-forks"}
{"state_code":"US_DEMO","lsir_score":"39+","count":"21","time_window":"3y","supervision_type":"PAROLE","district":"devils-lake"}
{"state_code":"US_DEMO","lsir_score":"39+","count":"19","time_window":"3y","supervision_type":"PAROLE","district":"wahpeton"}
{"state_code":"US_DEMO","lsir_score":"39+","count":"32","time_window":"3y","supervision_type":"PAROLE","district":"rolla"}
{"state_code":"US_DEMO","lsir_score":"39+","count":"112","time_window":"3y","supervision_type":"PAROLE","district":"washburn"}
{"state_code":"US_DEMO","lsir_score":"39+","count":"74","time_window":"3y","supervision_type":"PAROLE","district":"williston"}
{"state_code":"US_DEMO","lsir_score":"39+","count":"21","time_window":"3y","supervision_type":"PAROLE","district":"dickson"}
{"state_code":"US_DEMO","lsir_score":"39+","count":"20","time_window":"3y","supervision_type":"PAROLE","district":"grafton"}
{"state_code":"US_DEMO","lsir_score":"39+","count":"19","time_window":"3y","supervision_type":"PAROLE","district":"mandan"}
{"state_code":"US_DEMO","lsir_score":"39+","count":"30","time_window":"3y","supervision_type":"PAROLE","district":"bottineau"}
{"state_code":"US_DEMO","lsir_score":"39+","count":"35","time_window":"3y","supervision_type":"PAROLE","district":"oakes"}
{"state_code":"US_DEMO","lsir_score":"39+","count":"51","time_window":"3y","supervision_type":"PAROLE","district":"beulah"}
{"state_code":"US_DEMO","lsir_score":"39+","count":"87","time_window":"3y","supervision_type":"PROBATION","district":"bismarck"}
{"state_code":"US_DEMO","lsir_score":"39+","count":"23","time_window":"3y","supervision_type":"PROBATION","district":"jamestown"}
{"state_code":"US_DEMO","lsir_score":"39+","count":"21","time_window":"3y","supervision_type":"PROBATION","district":"minot"}
{"state_code":"US_DEMO","lsir_score":"39+","count":"19","time_window":"3y","supervision_type":"PROBATION","district":"fargo"}
{"state_code":"US_DEMO","lsir_score":"39+","count":"22","time_window":"3y","supervision_type":"PROBATION","district":"grand-forks"}
{"state_code":"US_DEMO","lsir_score":"39+","count":"19","time_window":"3y","supervision_type":"PROBATION","district":"devils-lake"}
{"state_code":"US_DEMO","lsir_score":"39+","count":"46","time_window":"3y","supervision_type":"PROBATION","district":"wahpeton"}
{"state_code":"US_DEMO","lsir_score":"39+","count":"8","time_window":"3y","supervision_type":"PROBATION","district":"rolla"}
{"state_code":"US_DEMO","lsir_score":"39+","count":"95","time_window":"3y","supervision_type":"PROBATION","district":"washburn"}
{"state_code":"US_DEMO","lsir_score":"39+","count":"34","time_window":"3y","supervision_type":"PROBATION","district":"williston"}
{"state_code":"US_DEMO","lsir_score":"39+","count":"39","time_window":"3y","supervision_type":"PROBATION","district":"dickson"}
{"state_code":"US_DEMO","lsir_score":"39+","count":"97","time_window":"3y","supervision_type":"PROBATION","district":"grafton"}
{"state_code":"US_DEMO","lsir_score":"39+","count":"35","time_window":"3y","supervision_type":"PROBATION","district":"mandan"}
{"state_code":"US_DEMO","lsir_score":"39+","count":"188","time_window":"3y","supervision_type":"PROBATION","district":"bottineau"}
{"state_code":"US_DEMO","lsir_score":"39+","count":"95","time_window":"3y","supervision_type":"PROBATION","district":"oakes"}
{"state_code":"US_DEMO","lsir_score":"39+","count":"16","time_window":"3y","supervision_type":"PROBATION","district":"beulah"}
